AppCenter/__init__.py
AppCenter/__main__.py
AppCenter/cli.py
AppCenter/manage.py
AppCenter/settings/__init__.py
AppCenter/settings/admin.py
AppCenter/settings/asgi.py
AppCenter/settings/dbrouters.py
AppCenter/settings/urls.py
AppCenter/settings/wsgi.py
AppCenter/simpleui/__init__.py
AppCenter/simpleui/apps.py
AppCenter/simpleui/forms.py
AppCenter/simpleui/widgets.py
AppCenter/simpleui/static/admin/css/autocomplete.css
AppCenter/simpleui/static/admin/css/base.css
AppCenter/simpleui/static/admin/css/changelists.css
AppCenter/simpleui/static/admin/css/dashboard.css
AppCenter/simpleui/static/admin/css/fonts.css
AppCenter/simpleui/static/admin/css/forms.css
AppCenter/simpleui/static/admin/css/login.css
AppCenter/simpleui/static/admin/css/responsive.css
AppCenter/simpleui/static/admin/css/responsive_rtl.css
AppCenter/simpleui/static/admin/css/rtl.css
AppCenter/simpleui/static/admin/css/ui.css
AppCenter/simpleui/static/admin/css/widgets.css
AppCenter/simpleui/static/admin/css/vendor/select2/LICENSE-SELECT2.md
AppCenter/simpleui/static/admin/css/vendor/select2/select2.css
AppCenter/simpleui/static/admin/css/vendor/select2/select2.min.css
AppCenter/simpleui/static/admin/fonts/LICENSE.txt
AppCenter/simpleui/static/admin/fonts/README.txt
AppCenter/simpleui/static/admin/fonts/Roboto-Bold-webfont.woff
AppCenter/simpleui/static/admin/fonts/Roboto-Light-webfont.woff
AppCenter/simpleui/static/admin/fonts/Roboto-Regular-webfont.woff
AppCenter/simpleui/static/admin/img/LICENSE
AppCenter/simpleui/static/admin/img/README.txt
AppCenter/simpleui/static/admin/img/calendar-icons.svg
AppCenter/simpleui/static/admin/img/icon-addlink.svg
AppCenter/simpleui/static/admin/img/icon-alert.svg
AppCenter/simpleui/static/admin/img/icon-calendar.svg
AppCenter/simpleui/static/admin/img/icon-changelink.svg
AppCenter/simpleui/static/admin/img/icon-clock.svg
AppCenter/simpleui/static/admin/img/icon-deletelink.svg
AppCenter/simpleui/static/admin/img/icon-no.svg
DjangoDjangoAppCenter-0.0.11.dist-info/AUTHORS
DjangoDjangoAppCenter-0.0.11.dist-info/METADATA
DjangoDjangoAppCenter-0.0.11.dist-info/WHEEL
DjangoDjangoAppCenter-0.0.11.dist-info/entry_points.txt
DjangoDjangoAppCenter-0.0.11.dist-info/pbr.json
DjangoDjangoAppCenter-0.0.11.dist-info/top_level.txt
DjangoDjangoAppCenter-0.0.11.dist-info/RECORD
